single_cycle/reg_file.v
module reg_file (
    input             clk,
    input             reset,
    input             rg_wren,      // Write Enable: 1 to write data
    input      [4:0]  rs1, rs2, rd, // Addresses for Source 1, Source 2, and Destination
    input      [31:0] write_data,   // Data to be stored in 'rd'
    output     [31:0] read_data1,   // Data output from 'rs1'
    output     [31:0] read_data2    // Data output from 'rs2'
);

    // Declare 32 registers of 32-bit width
    reg [31:0] registers [31:0];
    integer i;

    // Async Read: ALU gets data instantly when rs1/rs2 addresses change
    assign read_data1 = (rs1 == 5'b0) ? 32'b0 : registers[rs1];
    assign read_data2 = (rs2 == 5'b0) ? 32'b0 : registers[rs2];

    // Synchronous Write: Data is stored only on the Rising Edge of the clock
    always @(posedge clk or posedge reset) begin
        if (reset) begin
            for (i = 0; i < 32; i = i + 1) begin
                registers[i] <= 32'b0;
            end
        end else begin
            // Write to rd if wren is high AND rd is not x0
            if (rg_wren && (rd != 5'b0)) begin
                registers[rd] <= write_data;
            end
        end
    end

endmodule

single_cycle/reg_test.v
`timescale 1ns / 1ps

module top_test;
    reg clk, reset, wren;
    reg [4:0] rs1, rs2, rd;
    reg [31:0] w_data;
    wire [31:0] out1, out2;

    // Instantiate Register File
    reg_file rf (
        .clk(clk), .reset(reset), .rg_wren(wren),
        .rs1(rs1), .rs2(rs2), .rd(rd),
        .write_data(w_data), .read_data1(out1), .read_data2(out2)
    );

    // Clock Generation
    always #5 clk = ~clk;

    initial begin
        $dumpfile("reg_test.vcd");
        $dumpvars(0, top_test);
        
        clk = 0; reset = 1; wren = 0;
        #10 reset = 0;

        // Step 1: Write 32'd5 to Register x1
        rd = 5'd1; w_data = 32'd5; wren = 1;
        #10; 
        
        // Step 2: Write 32'd10 to Register x2
        rd = 5'd2; w_data = 32'd10; wren = 1;
        #10;
        
        // Step 3: Stop writing, Read x1 and x2
        wren = 0;
        rs1 = 5'd1; rs2 = 5'd2;
        #10;
        
        $display("Register x1: %d, Register x2: %d", out1, out2);
        $finish;
    end
endmodule

single_cycle/instr_mem.v
module instr_mem (
    input  [31:0] pc_addr,
    output [31:0] instruction
);
    reg [31:0] mem [0:255];  // 256 words = 1KB instruction memory
    
    assign instr = mem[pc_addr[9:2]]; // word-aligned: drop bottom 2 bits
    
    initial begin
        $readmemh("instr_mem.txt", mem); // load from hex file
    end
endmodule

single_cycle/pc.v
module pc (
    input             clk,
    input             reset,
    input      [31:0] pc_next,  // Next instruction address (from adder/branch logic)
    output reg [31:0] pc_out    // Current instruction address
);

    always @(posedge clk or posedge reset) begin
        if (reset) begin
            pc_out <= 32'b0;    // Reset vector: Start execution at address 0
        end else begin
            pc_out <= pc_next;   // Update to the next program address
        end
    end

endmodule

single_cycle/fetch_tb.v
`timescale 1ns / 1ps

module fetch_tb;
    reg clk;
    reg reset;
    wire [31:0] current_pc;
    wire [31:0] next_pc;
    wire [31:0] instr;

    // Instantiate PC
    pc my_pc (
        .clk(clk), .reset(reset), .pc_next(next_pc), .pc_out(current_pc)
    );

    // Instantiate Instruction Memory
    instr_mem my_mem (
        .pc_addr(current_pc), .instruction(instr)
    );

    // Simple single-cycle calculation: Next PC is always Current PC + 4
    assign next_pc = current_pc + 32'd4;

    // Clock generator (10ns period)
    always #5 clk = ~clk;

    initial begin
        $dumpfile("fetch_test.vcd");
        $dumpvars(0, fetch_tb);

        clk = 0; reset = 1;
        #12 reset = 0; // Release reset just after a clock edge

        #40; // Let it run for 4 clock cycles to pull instructions
        $finish;
    end
endmodule

single_cycle/alu.v
module alu (
    input  [31:0] a,
    input  [31:0] b,
    input  [3:0]  alu_ctrl,
    output reg [31:0] result,
    output zero
);
    assign zero = (result == 32'b0);
    
    always @(*) begin
        case (alu_ctrl)
            4'b0000: result = a + b;          // ADD
            4'b0001: result = a - b;          // SUB
            4'b0010: result = a & b;          // AND
            4'b0011: result = a | b;          // OR
            4'b0100: result = a ^ b;          // XOR
            4'b0101: result = a << b[4:0];    // SLL logical shift left
            4'b0110: result = a >> b[4:0];    // SRL logical shift right
            4'b0111: result = $signed(a) >>> b[4:0]; // SRA arithmetic shift right
            4'b1000: result = ($signed(a) < $signed(b)) ? 32'd1 : 32'd0; // SLT arithmetic shift left
            default: result = 32'b0;
        endcase
    end
endmodule

single_cycle/imm_gen.v
module imm_gen (
    input  [31:0] instr,    // The raw 32-bit instruction
    output reg [31:0] imm_ext  // The sign-extended 32-bit immediate
);

    always @(*) begin
        case (instr[6:0])
            7'b0010011: begin // I-type Arithmetic (addi, etc.)
                imm_ext = {{20{instr[31]}}, instr[31:20]};
            end
            7'b0000011: begin // I-type Load (lw)
                imm_ext = {{20{instr[31]}}, instr[31:20]};
            end
            7'b0100011: begin // S-type Store (sw)
                imm_ext = {{20{instr[31]}}, instr[31:25], instr[11:7]};
            end
            7'b1100011: begin // B-type Branch (beq)
                imm_ext = {{20{instr[31]}}, instr[7], instr[30:25], instr[11:8], 1'b0};
            end
            default: begin
                imm_ext = 32'b0; // Default fallback
            end
        endcase
    end

endmodule

single_cycle/control.v
module control_unit (
    input  [6:0] opcode,     // instr[6:0]
    input  [2:0] funct3,     // instr[14:12]
    input        funct7_bit, // instr[30]
    output reg   reg_write,  // Enables writing to Register File
    output reg   alu_src,    // 0: Selects Register 2, 1: Selects Immediate
    output reg   mem_to_reg, // 0: ALU result to Reg, 1: Data Memory to Reg
    output reg   mem_write,  // Enables writing to Data Memory
    output reg   mem_read,   // Enables reading from Data Memory
    output reg   branch,     // High for branch instructions (e.g., BEQ)
    output reg [3:0] alu_ctrl // 4-bit signal sent straight to the ALU
);

    reg [1:0] alu_op;

    // --- MAIN DECODER ---
    always @(*) begin
        case (opcode)
            7'b0110011: begin // R-type (e.g., add, sub)
                reg_write  = 1'b1;
                alu_src    = 1'b0; // Use register data 2
                mem_to_reg = 1'b0;
                mem_write  = 1'b0;
                mem_read   = 1'b0;
                branch     = 1'b0;
                alu_op     = 2'b10; // Look at funct3/funct7
            end
            7'b0010011: begin // I-type Arithmetic (e.g., addi)
                reg_write  = 1'b1;
                alu_src    = 1'b1; // Use the immediate value
                mem_to_reg = 1'b0;
                mem_write  = 1'b0;
                mem_read   = 1'b0;
                branch     = 1'b0;
                alu_op     = 2'b00; // Force an addition behavior
            end
            7'b0000011: begin // I-type Load (e.g., lw - load word)
                reg_write  = 1'b1;
                alu_src    = 1'b1; // Use immediate for address offset
                mem_to_reg = 1'b1; // Route memory output back to register
                mem_write  = 1'b0;
                mem_read   = 1'b1;
                branch     = 1'b0;
                alu_op     = 2'b00; // Requires address addition
            end
            7'b0100011: begin // S-type Store (e.g., sw - store word)
                reg_write  = 1'b0;
                alu_src    = 1'b1; // Use immediate for address offset
                mem_to_reg = 1'b0; // Don't care
                mem_write  = 1'b1;
                mem_read   = 1'b0;
                branch     = 1'b0;
                alu_op     = 2'b00; // Requires address addition
            end
            7'b1100011: begin // B-type Branch (e.g., beq)
                reg_write  = 1'b0;
                alu_src    = 1'b0; // Compare two registers
                mem_to_reg = 1'b0; // Don't care
                mem_write  = 1'b0;
                mem_read   = 1'b0;
                branch     = 1'b1;
                alu_op     = 2'b01; // Requires subtraction comparison
            end
            default: begin // Default Safe State
                reg_write  = 1'b0;
                alu_src    = 1'b0;
                mem_to_reg = 1'b0;
                mem_write  = 1'b0;
                mem_read   = 1'b0;
                branch     = 1'b0;
                alu_op     = 2'b00;
            end
        endcase
    end

    // --- ALU DECODER ---
    always @(*) begin
        case (alu_op)
            2'b00: alu_ctrl = 4'b0000; // Force ADD (for Fetch, Loads, Stores, addi)
            2'b01: alu_ctrl = 4'b0001; // Force SUB (for Branch comparisons)
            2'b10: begin               // R-Type tracking via funct codes
                case (funct3)
                    3'b000: alu_ctrl = (funct7_bit) ? 4'b0001 : 4'b0000; // SUB if funct7 bit high, else ADD
                    3'b111: alu_ctrl = 4'b0010; // AND
                    3'b110: alu_ctrl = 4'b0011; // OR
                    3'b100: alu_ctrl = 4'b0100; // XOR
                    3'b001: alu_ctrl = 4'b0101; // SLL (Shift Left Logical)
                    3'b101: alu_ctrl = (funct7_bit) ? 4'b0111 : 4'b0110; // SRA if high, else SRL
                    3'b010: alu_ctrl = 4'b1000; // SLT (Set Less Than)
                    default: alu_ctrl = 4'b0000;
                endcase
            end
            default: alu_ctrl = 4'b0000;
        endcase
    end

endmodule

single_cycle/riscv_top.v
module riscv_top (
    input clk,
    input reset
);

    // Internal Wires
    wire [31:0] pc_current;
    wire [31:0] pc_next;
    wire [31:0] instr;
    
    // Control Signals
    wire reg_write, alu_src, mem_to_reg, mem_write, mem_read, branch;
    wire [3:0] alu_ctrl;
    
    // Data Wires
    wire [31:0] rd_data1, rd_data2;
    wire [31:0] imm_ext;
    wire [31:0] alu_operand2;
    wire [31:0] alu_result;
    wire alu_zero;

    // 1. Program Counter Logic (Simple incremental for now: PC = PC + 4)
    assign pc_next = pc_current + 32'd4;
    
    pc my_pc (
        .clk(clk),
        .reset(reset),
        .pc_next(pc_next),
        .pc_out(pc_current)
    );

    // 2. Instruction Fetch
    instr_mem my_instr_mem (
        .pc_addr(pc_current),
        .instruction(instr)
    );

    // 3. Control Unit
    control_unit my_control (
        .opcode(instr[6:0]),
        .funct3(instr[14:12]),
        .funct7_bit(instr[30]),
        .reg_write(reg_write),
        .alu_src(alu_src),
        .mem_to_reg(mem_to_reg),
        .mem_write(mem_write),
        .mem_read(mem_read),
        .branch(branch),
        .alu_ctrl(alu_ctrl)
    );

    // 4. Register File
    reg_file my_reg_file (
        .clk(clk),
        .reset(reset),
        .rg_wren(reg_write),
        .rs1(instr[19:15]),
        .rs2(instr[24:20]),
        .rd(instr[11:7]),
        .write_data(alu_result), // Direct loopback for single-cycle ALU execution
        .read_data1(rd_data1),
        .read_data2(rd_data2)
    );

    // 5. Immediate Generator
    imm_gen my_imm_gen (
        .instr(instr),
        .imm_ext(imm_ext)
    );

    // 6. ALU Source Multiplexer (MUX)
    // If alu_src is 1, select immediate. If 0, select register data 2.
    assign alu_operand2 = (alu_src) ? imm_ext : rd_data2;

    // 7. Execution Engine (ALU)
    alu my_alu (
        .a(rd_data1),
        .b(alu_operand2),
        .alu_ctrl(alu_ctrl),
        .result(alu_result),
        .zero(alu_zero)
    );

endmodule

single_cycle/cpu_tb.v
`timescale 1ns / 1ps

module cpu_tb;
    reg clk;
    reg reset;

    // Instantiate your complete processor core
    riscv_top uut (
        .clk(clk),
        .reset(reset)
    );

    // Generate Clock (50MHz frequency -> 20ns period)
    always #10 clk = ~clk;

    initial begin
        // Setup GTKWave trace files
        $dumpfile("cpu_execution.vcd");
        $dumpvars(0, cpu_tb);

        // Assert System Reset to force starting state
        clk = 0; reset = 1;
        #25; 
        
        // Release Reset to begin instruction execution loop
        reset = 0;

        // Run long enough to loop through your program.txt file
        #100;
        
        $display("--- Execution Simulation Complete ---");
        $finish;
    end
endmodule

single_cycle/alu_tb.v
`timescale 1ns / 1ps

module alu_tb;
    reg  [31:0] a, b;
    reg  [3:0]  ctrl;
    wire [31:0] res;
    wire        z;

    // Instantiate the ALU
    alu uut (
        .a(a), .b(b), .alu_ctrl(ctrl), .result(res), .zero(z)
    );

    initial begin
        // For GTKWave viewing
        $dumpfile("alu_test.vcd");
        $dumpvars(0, alu_tb);

        // Test 1: Addition (5 + 10)
        a = 32'd5; b = 32'd10; ctrl = 4'b0000;
        #10; $display("ADD: %d + %d = %d", a, b, res);

        // Test 2: Subtraction (20 - 7)
        a = 32'd20; b = 32'd7; ctrl = 4'b0001;
        #10; $display("SUB: %d - %d = %d", a, b, res);

        // Test 3: Logical AND (0xFFFF0000 & 0x00FFFF00)
        a = 32'hFFFF0000; b = 32'h00FFFF00; ctrl = 4'b0010;
        #10; $display("AND: %h & %h = %h", a, b, res);

        // Test 4: Shift Left (1 << 4)
        a = 32'd1; b = 32'd4; ctrl = 4'b0101;
        #10; $display("SLL: %d << %d = %d", a, b, res);

        $finish;
    end
endmodule

single_cycle/alu_test.vcd
$date
	Wed Jun 03 20:34:08 2026
$end
$version
	Icarus Verilog
$end
$timescale
	1ps
$end
$scope module alu_tb $end
$var wire 1 ! z $end
$var wire 32 " res [31:0] $end
$var reg 32 # a [31:0] $end
$var reg 32 $ b [31:0] $end
$var reg 4 % ctrl [3:0] $end
$scope module uut $end
$var wire 32 & a [31:0] $end
$var wire 4 ' alu_ctrl [3:0] $end
$var wire 32 ( b [31:0] $end
$var wire 1 ! zero $end
$var reg 32 ) result [31:0] $end
$upscope $end
$upscope $end
$scope module cpu_tb $end
$var reg 1 * clk $end
$var reg 1 + reset $end
$scope module uut $end
$var wire 1 * clk $end
$var wire 32 , instr [31:0] $end
$var wire 1 + reset $end
$var wire 1 - reg_write $end
$var wire 32 . rd_data2 [31:0] $end
$var wire 32 / rd_data1 [31:0] $end
$var wire 32 0 pc_next [31:0] $end
$var wire 32 1 pc_current [31:0] $end
$var wire 1 2 mem_write $end
$var wire 1 3 mem_to_reg $end
$var wire 1 4 mem_read $end
$var wire 32 5 imm_ext [31:0] $end
$var wire 1 6 branch $end
$var wire 1 7 alu_zero $end
$var wire 1 8 alu_src $end
$var wire 32 9 alu_result [31:0] $end
$var wire 32 : alu_operand2 [31:0] $end
$var wire 4 ; alu_ctrl [3:0] $end
$scope module my_alu $end
$var wire 32 < b [31:0] $end
$var wire 1 7 zero $end
$var wire 4 = alu_ctrl [3:0] $end
$var wire 32 > a [31:0] $end
$var reg 32 ? result [31:0] $end
$upscope $end
$scope module my_control $end
$var wire 3 @ funct3 [2:0] $end
$var wire 1 A funct7_bit $end
$var wire 7 B opcode [6:0] $end
$var reg 4 C alu_ctrl [3:0] $end
$var reg 2 D alu_op [1:0] $end
$var reg 1 8 alu_src $end
$var reg 1 6 branch $end
$var reg 1 4 mem_read $end
$var reg 1 3 mem_to_reg $end
$var reg 1 2 mem_write $end
$var reg 1 - reg_write $end
$upscope $end
$scope module my_imm_gen $end
$var wire 32 E instr [31:0] $end
$var reg 32 F imm_ext [31:0] $end
$upscope $end
$scope module my_instr_mem $end
$var wire 32 G instruction [31:0] $end
$var wire 32 H pc_addr [31:0] $end
$var wire 1 I instr $end
$upscope $end
$scope module my_pc $end
$var wire 1 * clk $end
$var wire 32 J pc_next [31:0] $end
$var wire 1 + reset $end
$var reg 32 K pc_out [31:0] $end
$upscope $end
$scope module my_reg_file $end
$var wire 1 * clk $end
$var wire 5 L rd [4:0] $end
$var wire 1 + reset $end
$var wire 1 - rg_wren $end
$var wire 5 M rs1 [4:0] $end
$var wire 5 N rs2 [4:0] $end
$var wire 32 O write_data [31:0] $end
$var wire 32 P read_data2 [31:0] $end
$var wire 32 Q read_data1 [31:0] $end
$var integer 32 R i [31:0] $end
$upscope $end
$upscope $end
$upscope $end
$scope module fetch_tb $end
$var wire 32 S instr [31:0] $end
$var wire 32 T next_pc [31:0] $end
$var wire 32 U current_pc [31:0] $end
$var reg 1 V clk $end
$var reg 1 W reset $end
$scope module my_mem $end
$var wire 32 X instruction [31:0] $end
$var wire 32 Y pc_addr [31:0] $end
$var wire 1 Z instr $end
$upscope $end
$scope module my_pc $end
$var wire 1 V clk $end
$var wire 32 [ pc_next [31:0] $end
$var wire 1 W reset $end
$var reg 32 \ pc_out [31:0] $end
$upscope $end
$upscope $end
$scope module top_test $end
$var wire 32 ] out2 [31:0] $end
$var wire 32 ^ out1 [31:0] $end
$var reg 1 _ clk $end
$var reg 5 ` rd [4:0] $end
$var reg 1 a reset $end
$var reg 5 b rs1 [4:0] $end
$var reg 5 c rs2 [4:0] $end
$var reg 32 d w_data [31:0] $end
$var reg 1 e wren $end
$scope module rf $end
$var wire 1 _ clk $end
$var wire 5 f rd [4:0] $end
$var wire 1 a reset $end
$var wire 1 e rg_wren $end
$var wire 5 g rs1 [4:0] $end
$var wire 5 h rs2 [4:0] $end
$var wire 32 i write_data [31:0] $end
$var wire 32 j read_data2 [31:0] $end
$var wire 32 k read_data1 [31:0] $end
$var integer 32 l i [31:0] $end
$upscope $end
$upscope $end
$enddefinitions $end
$comment Show the parameter values. $end
$dumpall
$end
#0
$dumpvars
b100000 l
bx k
bx j
bx i
bx h
bx g
bx f
0e
bx d
bx c
bx b
1a
bx `
0_
bx ^
bx ]
b0 \
b100 [
1Z
b0 Y
bz X
1W
0V
b0 U
b100 T
bz S
b100000 R
bx Q
bx P
bx O
bz N
bz M
bz L
b0 K
b100 J
1I
b0 H
bz G
b0 F
bz E
b0 D
b0 C
bz B
zA
bz @
bx ?
bx >
b0 =
bx <
b0 ;
bx :
bx 9
08
x7
06
b0 5
04
03
02
b0 1
b100 0
bx /
bx .
0-
bz ,
1+
0*
b1111 )
b1010 (
b0 '
b101 &
b0 %
b1010 $
b101 #
b1111 "
0!
$end
#5000
b100000 l
1_
1V
#10000
b100000 R
b1101 "
b1101 )
0_
0V
1e
b101 d
b101 i
b1 `
b1 f
0a
1*
b1 %
b1 '
b111 $
b111 (
b10100 #
b10100 &
#12000
0W
#15000
b1000 T
b1000 [
b100 U
b100 Y
b100 \
1_
1V
#20000
b111111110000000000000000 "
b111111110000000000000000 )
0_
0V
b1010 d
b1010 i
b10 `
b10 f
0*
b10 %
b10 '
b111111111111111100000000 $
b111111111111111100000000 (
b11111111111111110000000000000000 #
b11111111111111110000000000000000 &
#25000
b1100 T
b1100 [
b1000 U
b1000 Y
b1000 \
1_
1V
0+
#30000
b1000 0
b1000 J
b100 1
b100 H
b100 K
b1010 ]
b1010 j
b101 ^
b101 k
b10000 "
b10000 )
0_
0V
b10 c
b10 h
b1 b
b1 g
0e
1*
b101 %
b101 '
b100 $
b100 (
b1 #
b1 &
#35000
0Z
b10000 T
b10000 [
b1100 U
b1100 Y
b1100 \
1_
1V
